interface/__init__.py
interface/analyzeOutput.js
interface/buildTestCases.js
interface/cli.py
interface/index.js
interface/index.mjs
interface/package.json
interface/pipeoptimizer.js
interface/tempCodeRunnerFile.js
interface/node_modules/@babel/code-frame/lib/index.js
interface/node_modules/@babel/helper-validator-identifier/lib/identifier.js
interface/node_modules/@babel/helper-validator-identifier/lib/index.js
interface/node_modules/@babel/helper-validator-identifier/lib/keyword.js
interface/node_modules/@cronvel/get-pixels/node-pixels.js
interface/node_modules/@inquirer/checkbox/dist/commonjs/index.js
interface/node_modules/@inquirer/checkbox/dist/esm/index.js
interface/node_modules/@inquirer/confirm/dist/commonjs/index.js
interface/node_modules/@inquirer/confirm/dist/esm/index.js
interface/node_modules/@inquirer/core/dist/commonjs/index.js
interface/node_modules/@inquirer/core/dist/commonjs/lib/Separator.js
interface/node_modules/@inquirer/core/dist/commonjs/lib/create-prompt.js
interface/node_modules/@inquirer/core/dist/commonjs/lib/errors.js
interface/node_modules/@inquirer/core/dist/commonjs/lib/hook-engine.js
interface/node_modules/@inquirer/core/dist/commonjs/lib/key.js
interface/node_modules/@inquirer/core/dist/commonjs/lib/make-theme.js
interface/node_modules/@inquirer/core/dist/commonjs/lib/promise-polyfill.js
interface/node_modules/@inquirer/core/dist/commonjs/lib/screen-manager.js
interface/node_modules/@inquirer/core/dist/commonjs/lib/theme.js
interface/node_modules/@inquirer/core/dist/commonjs/lib/use-effect.js
interface/node_modules/@inquirer/core/dist/commonjs/lib/use-keypress.js
interface/node_modules/@inquirer/core/dist/commonjs/lib/use-memo.js
interface/node_modules/@inquirer/core/dist/commonjs/lib/use-prefix.js
interface/node_modules/@inquirer/core/dist/commonjs/lib/use-ref.js
interface/node_modules/@inquirer/core/dist/commonjs/lib/use-state.js
interface/node_modules/@inquirer/core/dist/commonjs/lib/utils.js
interface/node_modules/hosted-git-info/git-host-info.js
interface/node_modules/hosted-git-info/git-host.js
interface/node_modules/hosted-git-info/index.js
testronaut-0.1.10.dist-info/METADATA
testronaut-0.1.10.dist-info/WHEEL
testronaut-0.1.10.dist-info/entry_points.txt
testronaut-0.1.10.dist-info/top_level.txt
testronaut-0.1.10.dist-info/RECORD
